Metadata-Version: 1.1
Name: chapman2
Version: 0.0.0.dev1
Summary: Chapman2 Task Queue
Home-page: UNKNOWN
Author: Rick Copeland
Author-email: rick@ehtcares.com
License: UNKNOWN
Platform: UNKNOWN
Classifier: Programming Language :: Python
